macroframe_forecast/MFF.py
macroframe_forecast/MFF_mixed_frequency.py
macroframe_forecast/__init__.py
macroframe_forecast/examples.py
macroframe_forecast/utils.py
macroframe_forecast-0.1.6.dist-info/METADATA
macroframe_forecast-0.1.6.dist-info/WHEEL
macroframe_forecast-0.1.6.dist-info/licenses/LICENSE
macroframe_forecast-0.1.6.dist-info/RECORD
