Metadata-Version: 2.4
Name: macroframe-forecast
Version: 0.1.6
Summary: Macroframework forecasting with accounting identities
Project-URL: homepage, https://github.com/sakaiando/macroframe-forecast
Project-URL: repository, https://github.com/sakaiando/macroframe-forecast
Maintainer-email: Sakai Ando <sando@imf.org>, Sultan Orazbayev <sorazbayev@imf.org>
License-File: LICENSE
Keywords: econometrics,forecasting,high-dimensional forecasting,macroeconomic identities,macroframework
Classifier: Intended Audience :: Developers
Classifier: Intended Audience :: Education
Classifier: Intended Audience :: Other Audience
Classifier: Intended Audience :: Science/Research
Classifier: Programming Language :: Python :: 3 :: Only
Classifier: Programming Language :: Python :: 3.11
Classifier: Programming Language :: Python :: 3.12
Classifier: Topic :: Scientific/Engineering
Classifier: Topic :: Scientific/Engineering :: Information Analysis
Classifier: Topic :: Scientific/Engineering :: Mathematics
Requires-Python: >=3.11
Requires-Dist: cvxpy>=1.5.3
Requires-Dist: dask[dataframe]>=2024.8.1
Requires-Dist: distributed>=2024.2.0
Requires-Dist: matplotlib>=3.10.3
Requires-Dist: numpy>=1.26.3
Requires-Dist: pandas>=2.2.0
Requires-Dist: scikit-learn>=1.4.0
Requires-Dist: scipy>=1.12.0
Requires-Dist: sktime>=0.27.0
Requires-Dist: statsmodels>=0.14.4
Requires-Dist: sympy>=1.12
